mzapy/__init__.py
mzapy/_config.py
mzapy/_util.py
mzapy/calibration.py
mzapy/dda.py
mzapy/isotopes.py
mzapy/peaks.py
mzapy/view.py
mzapy-1.8.0.dist-info/METADATA
mzapy-1.8.0.dist-info/WHEEL
mzapy-1.8.0.dist-info/top_level.txt
mzapy-1.8.0.dist-info/RECORD
